LICENSE.txt
MANIFEST.in
README.md
setup.cfg
setup.py
include/i2cdriver.h
include/spidriver.h
serbus/__init__.py
serbus/pyi2cdev.c
serbus/pyspidev.c
serbus.egg-info/PKG-INFO
serbus.egg-info/SOURCES.txt
serbus.egg-info/dependency_links.txt
serbus.egg-info/top_level.txt
src/i2cdriver.c
src/spidriver.c