Metadata-Version: 1.1
Name: serbus
Version: 1.0.5
Summary: A Python package for I2C and SPI serial bus communication on GNU/Linux systems.
Home-page: https://github.com/graycatlabs/serbus
Author: Alexander Hiam
Author-email: alex@graycat.io
License: MIT License
Download-URL: https://github.com/graycatlabs/serbus/tarball/v1.0.5
Keywords: I2C,SPI,serial,Linux
Platform: UNKNOWN
Classifier: License :: OSI Approved :: MIT License
Classifier: Operating System :: POSIX :: Linux
Classifier: Topic :: Software Development :: Embedded Systems
Classifier: Topic :: Software Development :: Libraries :: Python Modules
Classifier: Topic :: System :: Hardware
